{
    "Version": 1,
    "Name": "洗翠索罗亚",
    "ModelID": "4dbc09284be1440d81f6c5ff4d789713",
    "FileReferences": {
        "Icon": "洗翠索罗亚.jpg",
        "Model": "洗翠索罗亚.model3.json",
        "IdleAnimation": "",
        "IdleAnimationWhenTrackingLost": ""
    },
    "ModelSaveMetadata": {
        "LastSavedVTubeStudioVersion": "1.28.15",
        "LastSavedPlatform": "Steam",
        "LastSavedDateUTC": "Tuesday, 04 June 2024, 11:17:48",
        "LastSavedDateLocalTime": "Tuesday, 04 June 2024, 19:17:48",
        "LastSavedDateUnixMillisecondTimestamp": "1717499868447"
    },
    "SavedModelPosition": {
        "Position": {
            "x": 9.14798355102539,
            "y": 1.7488784790039063,
            "z": 0.0
        },
        "Rotation": {
            "x": 0.0,
            "y": 0.0,
            "z": 0.0,
            "w": 1.0
        },
        "Scale": {
            "x": 1.0,
            "y": 1.0,
            "z": 1.0
        }
    },
    "ModelPositionMovement": {
        "Use": true,
        "X": 6,
        "Y": 8,
        "Z": 11,
        "SmoothingX": 10,
        "SmoothingY": 10,
        "SmoothingZ": 10
    },
    "ItemSettings": {
        "OnlyMoveWhenPinned": false,
        "AllowNormalHotkeyTriggers": true,
        "Multiplier_HeadAngleX": 1.0,
        "Multiplier_HeadAngleY": 1.0,
        "Multiplier_HeadAngleZ": 1.0,
        "Shift_HeadAngleX": 0.0,
        "Shift_HeadAngleY": 0.0,
        "Smoothing_HeadAngleX": 15.0,
        "Smoothing_HeadAngleY": 15.0,
        "Smoothing_HeadAngleZ": 15.0
    },
    "PhysicsSettings": {
        "Use": true,
        "UseLegacyPhysics": false,
        "Live2DPhysicsFPS": 3,
        "PhysicsStrength": 50,
        "WindStrength": 0,
        "DraggingPhysicsStrength": 0
    },
    "GeneralSettings": {
        "TimeUntilTrackingLostIdleAnimation": 0.0,
        "WorkshopSharingForbidden": true,
        "EnableExpressionSaving": true
    },
    "ParameterSettings": [
        {
            "Folder": "",
            "Name": "Face Left/Right Rotation",
            "Input": "FaceAngleX",
            "InputRangeLower": -30.0,
            "InputRangeUpper": 30.0,
            "OutputRangeLower": -30.0,
            "OutputRangeUpper": 30.0,
            "ClampInput": false,
            "ClampOutput": false,
            "UseBlinking": false,
            "UseBreathing": false,
            "OutputLive2D": "ParamAngleX",
            "Smoothing": 15,
            "Minimized": false
        },
        {
            "Folder": "",
            "Name": "Face Up/Down Rotation",
            "Input": "FaceAngleY",
            "InputRangeLower": -20.0,
            "InputRangeUpper": 20.0,
            "OutputRangeLower": -30.0,
            "OutputRangeUpper": 30.0,
            "ClampInput": false,
            "ClampOutput": false,
            "UseBlinking": false,
            "UseBreathing": false,
            "OutputLive2D": "ParamAngleY",
            "Smoothing": 15,
            "Minimized": false
        },
        {
            "Folder": "",
            "Name": "Face Lean Rotation",
            "Input": "FaceAngleZ",
            "InputRangeLower": -30.0,
            "InputRangeUpper": 30.0,
            "OutputRangeLower": -30.0,
            "OutputRangeUpper": 30.0,
            "ClampInput": false,
            "ClampOutput": false,
            "UseBlinking": false,
            "UseBreathing": false,
            "OutputLive2D": "ParamAngleZ",
            "Smoothing": 30,
            "Minimized": false
        },
        {
            "Folder": "",
            "Name": "Body Rotation X",
            "Input": "FaceAngleX",
            "InputRangeLower": -30.0,
            "InputRangeUpper": 30.0,
            "OutputRangeLower": -10.0,
            "OutputRangeUpper": 10.0,
            "ClampInput": false,
            "ClampOutput": false,
            "UseBlinking": false,
            "UseBreathing": false,
            "OutputLive2D": "ParamBodyAngleX",
            "Smoothing": 20,
            "Minimized": false
        },
        {
            "Folder": "",
            "Name": "Body Rotation Y",
            "Input": "FaceAngleY",
            "InputRangeLower": -30.0,
            "InputRangeUpper": 30.0,
            "OutputRangeLower": -10.0,
            "OutputRangeUpper": 10.0,
            "ClampInput": false,
            "ClampOutput": false,
            "UseBlinking": false,
            "UseBreathing": false,
            "OutputLive2D": "ParamBodyAngleY",
            "Smoothing": 20,
            "Minimized": false
        },
        {
            "Folder": "",
            "Name": "Body Rotation Z",
            "Input": "FaceAngleZ",
            "InputRangeLower": -30.0,
            "InputRangeUpper": 30.0,
            "OutputRangeLower": -10.0,
            "OutputRangeUpper": 10.0,
            "ClampInput": false,
            "ClampOutput": false,
            "UseBlinking": false,
            "UseBreathing": false,
            "OutputLive2D": "ParamBodyAngleZ",
            "Smoothing": 20,
            "Minimized": false
        },
        {
            "Folder": "",
            "Name": "Eye Open Left",
            "Input": "EyeOpenLeft",
            "InputRangeLower": 0.0,
            "InputRangeUpper": 1.0,
            "OutputRangeLower": 0.0,
            "OutputRangeUpper": 1.899999976158142,
            "ClampInput": false,
            "ClampOutput": false,
            "UseBlinking": false,
            "UseBreathing": false,
            "OutputLive2D": "ParamEyeLOpen",
            "Smoothing": 10,
            "Minimized": false
        },
        {
            "Folder": "",
            "Name": "Eye Smile Left",
            "Input": "MouthSmile",
            "InputRangeLower": 0.0,
            "InputRangeUpper": 1.0,
            "OutputRangeLower": 0.0,
            "OutputRangeUpper": 1.0,
            "ClampInput": false,
            "ClampOutput": false,
            "UseBlinking": false,
            "UseBreathing": false,
            "OutputLive2D": "ParamEyeLSmile",
            "Smoothing": 10,
            "Minimized": false
        },
        {
            "Folder": "",
            "Name": "Eye Open Right",
            "Input": "EyeOpenRight",
            "InputRangeLower": 0.0,
            "InputRangeUpper": 1.0,
            "OutputRangeLower": 0.0,
            "OutputRangeUpper": 1.899999976158142,
            "ClampInput": false,
            "ClampOutput": false,
            "UseBlinking": false,
            "UseBreathing": false,
            "OutputLive2D": "ParamEyeROpen",
            "Smoothing": 10,
            "Minimized": false
        },
        {
            "Folder": "",
            "Name": "Eye Smile Right",
            "Input": "MouthSmile",
            "InputRangeLower": 0.0,
            "InputRangeUpper": 1.0,
            "OutputRangeLower": 0.0,
            "OutputRangeUpper": 1.0,
            "ClampInput": false,
            "ClampOutput": false,
            "UseBlinking": false,
            "UseBreathing": false,
            "OutputLive2D": "ParamEyeRSmile",
            "Smoothing": 10,
            "Minimized": false
        },
        {
            "Folder": "",
            "Name": "Eye X",
            "Input": "EyeRightX",
            "InputRangeLower": -1.0,
            "InputRangeUpper": 1.0,
            "OutputRangeLower": 1.0,
            "OutputRangeUpper": -1.0,
            "ClampInput": false,
            "ClampOutput": false,
            "UseBlinking": false,
            "UseBreathing": false,
            "OutputLive2D": "ParamEyeBallX",
            "Smoothing": 8,
            "Minimized": false
        },
        {
            "Folder": "",
            "Name": "Eye Y",
            "Input": "EyeRightY",
            "InputRangeLower": -1.0,
            "InputRangeUpper": 1.0,
            "OutputRangeLower": -1.0,
            "OutputRangeUpper": 1.0,
            "ClampInput": false,
            "ClampOutput": false,
            "UseBlinking": false,
            "UseBreathing": false,
            "OutputLive2D": "ParamEyeBallY",
            "Smoothing": 8,
            "Minimized": false
        },
        {
            "Folder": "",
            "Name": "Mouth Smile",
            "Input": "MouthSmile",
            "InputRangeLower": 0.4000000059604645,
            "InputRangeUpper": 0.800000011920929,
            "OutputRangeLower": -1.0,
            "OutputRangeUpper": 1.0,
            "ClampInput": false,
            "ClampOutput": true,
            "UseBlinking": false,
            "UseBreathing": false,
            "OutputLive2D": "ParamMouthForm",
            "Smoothing": 0,
            "Minimized": false
        },
        {
            "Folder": "",
            "Name": "Mouth Open",
            "Input": "MouthOpen",
            "InputRangeLower": 0.0,
            "InputRangeUpper": 1.0,
            "OutputRangeLower": 0.0,
            "OutputRangeUpper": 2.0999999046325685,
            "ClampInput": false,
            "ClampOutput": false,
            "UseBlinking": false,
            "UseBreathing": false,
            "OutputLive2D": "ParamMouthOpenY",
            "Smoothing": 0,
            "Minimized": false
        },
        {
            "Folder": "",
            "Name": "Brow Height Left",
            "Input": "Brows",
            "InputRangeLower": 0.0,
            "InputRangeUpper": 1.0,
            "OutputRangeLower": -1.0,
            "OutputRangeUpper": 1.0,
            "ClampInput": false,
            "ClampOutput": false,
            "UseBlinking": false,
            "UseBreathing": false,
            "OutputLive2D": "ParamBrowLY",
            "Smoothing": 10,
            "Minimized": false
        },
        {
            "Folder": "",
            "Name": "Brow Height Right",
            "Input": "Brows",
            "InputRangeLower": 0.0,
            "InputRangeUpper": 1.0,
            "OutputRangeLower": -1.0,
            "OutputRangeUpper": 1.0,
            "ClampInput": false,
            "ClampOutput": false,
            "UseBlinking": false,
            "UseBreathing": false,
            "OutputLive2D": "ParamBrowRY",
            "Smoothing": 10,
            "Minimized": false
        },
        {
            "Folder": "",
            "Name": "Brow Form Left",
            "Input": "Brows",
            "InputRangeLower": 0.0,
            "InputRangeUpper": 1.0,
            "OutputRangeLower": -1.0,
            "OutputRangeUpper": 1.0,
            "ClampInput": false,
            "ClampOutput": false,
            "UseBlinking": false,
            "UseBreathing": false,
            "OutputLive2D": "ParamBrowLForm",
            "Smoothing": 15,
            "Minimized": false
        },
        {
            "Folder": "",
            "Name": "Brow Form Right",
            "Input": "Brows",
            "InputRangeLower": 0.0,
            "InputRangeUpper": 1.0,
            "OutputRangeLower": -1.0,
            "OutputRangeUpper": 1.0,
            "ClampInput": false,
            "ClampOutput": false,
            "UseBlinking": false,
            "UseBreathing": false,
            "OutputLive2D": "ParamBrowRForm",
            "Smoothing": 15,
            "Minimized": false
        },
        {
            "Folder": "",
            "Name": "Blush when smiling",
            "Input": "MouthSmile",
            "InputRangeLower": 0.0,
            "InputRangeUpper": 1.0,
            "OutputRangeLower": 0.5,
            "OutputRangeUpper": 1.0,
            "ClampInput": false,
            "ClampOutput": false,
            "UseBlinking": false,
            "UseBreathing": false,
            "OutputLive2D": "ParamCheek",
            "Smoothing": 45,
            "Minimized": false
        },
        {
            "Folder": "",
            "Name": "Auto Breath",
            "Input": "",
            "InputRangeLower": 0.0,
            "InputRangeUpper": 1.0,
            "OutputRangeLower": 0.0,
            "OutputRangeUpper": 1.0,
            "ClampInput": false,
            "ClampOutput": false,
            "UseBlinking": false,
            "UseBreathing": true,
            "OutputLive2D": "ParamBreath",
            "Smoothing": 0,
            "Minimized": false
        },
        {
            "Folder": "",
            "Name": "速度1",
            "Input": "MouthSmile",
            "InputRangeLower": 0.699999988079071,
            "InputRangeUpper": 1.0,
            "OutputRangeLower": 1.0,
            "OutputRangeUpper": 0.0,
            "ClampInput": false,
            "ClampOutput": true,
            "UseBlinking": false,
            "UseBreathing": false,
            "OutputLive2D": "Param80",
            "Smoothing": 65,
            "Minimized": false
        },
        {
            "Folder": "",
            "Name": "速度2",
            "Input": "MouthSmile",
            "InputRangeLower": 0.699999988079071,
            "InputRangeUpper": 1.0,
            "OutputRangeLower": 0.0,
            "OutputRangeUpper": 2.0,
            "ClampInput": false,
            "ClampOutput": true,
            "UseBlinking": false,
            "UseBreathing": false,
            "OutputLive2D": "Param81",
            "Smoothing": 20,
            "Minimized": false
        }
    ],
    "Hotkeys": [
        {
            "HotkeyID": "f2d8109158c946b1b6a2416ce14f3112",
            "Name": "惊讶",
            "Action": "ToggleExpression",
            "File": "惊讶.exp3.json",
            "Folder": "",
            "Position": {
                "X": 0.0,
                "Y": 0.0,
                "Z": 0.0,
                "Rotation": 0.0
            },
            "ColorOverlay": {
                "On": false,
                "IsStaticColor": false,
                "Display": -1,
                "WindowName": "",
                "IncludeLeft": false,
                "IncludeMid": false,
                "IncludeRight": false,
                "BaseValue": 0,
                "OverlayValue": 0,
                "Smoothing": 0,
                "IncludeItems": false,
                "StaticColor": {
                    "r": 0.0,
                    "g": 0.0,
                    "b": 0.0,
                    "a": 1.0
                }
            },
            "ColorScreenMultiplyPreset": {
                "ArtMeshMultiplyAndScreenColors": []
            },
            "HandGestureSettings": {
                "GestureLeft": "",
                "GestureRight": "",
                "GestureCombinator": "AND",
                "AllowMirroredGesture": false,
                "DeactivateExpWhenGestureNotDetected": false,
                "SecondsUntilDetection": 0.5,
                "SecondsDetected": 0.0,
                "PercentDetected": 0.0
            },
            "LoadModelSettings": {
                "LoadAtCurrentPosition": true
            },
            "Triggers": {
                "Trigger1": "Numpad1",
                "Trigger2": "",
                "Trigger3": "",
                "ScreenButton": -1
            },
            "IsGlobal": true,
            "IsActive": true,
            "Minimized": false,
            "StopsOnLastFrame": false,
            "DeactivateAfterKeyUp": false,
            "OnlyLoadOneRandomItem": false,
            "DeactivateAfterSeconds": false,
            "DeactivateAfterSecondsAmount": 10.0,
            "FadeSecondsAmount": 0.5,
            "OnScreenHotkeyColor": {
                "r": 1.0,
                "g": 1.0,
                "b": 1.0,
                "a": 1.0
            }
        },
        {
            "HotkeyID": "60c22bea0cf54cb682df5ba6c358b55e",
            "Name": "水印",
            "Action": "ToggleExpression",
            "File": "水印.exp3.json",
            "Folder": "",
            "Position": {
                "X": 0.0,
                "Y": 0.0,
                "Z": 0.0,
                "Rotation": 0.0
            },
            "ColorOverlay": {
                "On": false,
                "IsStaticColor": false,
                "Display": -1,
                "WindowName": "",
                "IncludeLeft": false,
                "IncludeMid": false,
                "IncludeRight": false,
                "BaseValue": 0,
                "OverlayValue": 0,
                "Smoothing": 0,
                "IncludeItems": false,
                "StaticColor": {
                    "r": 0.0,
                    "g": 0.0,
                    "b": 0.0,
                    "a": 1.0
                }
            },
            "ColorScreenMultiplyPreset": {
                "ArtMeshMultiplyAndScreenColors": []
            },
            "HandGestureSettings": {
                "GestureLeft": "",
                "GestureRight": "",
                "GestureCombinator": "AND",
                "AllowMirroredGesture": false,
                "DeactivateExpWhenGestureNotDetected": false,
                "SecondsUntilDetection": 0.5,
                "SecondsDetected": 0.0,
                "PercentDetected": 0.0
            },
            "LoadModelSettings": {
                "LoadAtCurrentPosition": true
            },
            "Triggers": {
                "Trigger1": "Space",
                "Trigger2": "",
                "Trigger3": "",
                "ScreenButton": -1
            },
            "IsGlobal": true,
            "IsActive": true,
            "Minimized": false,
            "StopsOnLastFrame": false,
            "DeactivateAfterKeyUp": false,
            "OnlyLoadOneRandomItem": false,
            "DeactivateAfterSeconds": false,
            "DeactivateAfterSecondsAmount": 10.0,
            "FadeSecondsAmount": 0.5,
            "OnScreenHotkeyColor": {
                "r": 1.0,
                "g": 1.0,
                "b": 1.0,
                "a": 1.0
            }
        },
        {
            "HotkeyID": "a7a5bb20d595416794e89dae1ef684d2",
            "Name": "生气",
            "Action": "ToggleExpression",
            "File": "生气.exp3.json",
            "Folder": "",
            "Position": {
                "X": 0.0,
                "Y": 0.0,
                "Z": 0.0,
                "Rotation": 0.0
            },
            "ColorOverlay": {
                "On": false,
                "IsStaticColor": false,
                "Display": -1,
                "WindowName": "",
                "IncludeLeft": false,
                "IncludeMid": false,
                "IncludeRight": false,
                "BaseValue": 0,
                "OverlayValue": 0,
                "Smoothing": 0,
                "IncludeItems": false,
                "StaticColor": {
                    "r": 0.0,
                    "g": 0.0,
                    "b": 0.0,
                    "a": 1.0
                }
            },
            "ColorScreenMultiplyPreset": {
                "ArtMeshMultiplyAndScreenColors": []
            },
            "HandGestureSettings": {
                "GestureLeft": "",
                "GestureRight": "",
                "GestureCombinator": "AND",
                "AllowMirroredGesture": false,
                "DeactivateExpWhenGestureNotDetected": false,
                "SecondsUntilDetection": 0.5,
                "SecondsDetected": 0.0,
                "PercentDetected": 0.0
            },
            "LoadModelSettings": {
                "LoadAtCurrentPosition": true
            },
            "Triggers": {
                "Trigger1": "Numpad2",
                "Trigger2": "",
                "Trigger3": "",
                "ScreenButton": -1
            },
            "IsGlobal": true,
            "IsActive": true,
            "Minimized": false,
            "StopsOnLastFrame": false,
            "DeactivateAfterKeyUp": false,
            "OnlyLoadOneRandomItem": false,
            "DeactivateAfterSeconds": false,
            "DeactivateAfterSecondsAmount": 10.0,
            "FadeSecondsAmount": 0.5,
            "OnScreenHotkeyColor": {
                "r": 1.0,
                "g": 1.0,
                "b": 1.0,
                "a": 1.0
            }
        },
        {
            "HotkeyID": "50e4cfbefbf54e7cb80697f7be772b91",
            "Name": "脸红",
            "Action": "ToggleExpression",
            "File": "脸红.exp3.json",
            "Folder": "",
            "Position": {
                "X": 0.0,
                "Y": 0.0,
                "Z": 0.0,
                "Rotation": 0.0
            },
            "ColorOverlay": {
                "On": false,
                "IsStaticColor": false,
                "Display": -1,
                "WindowName": "",
                "IncludeLeft": false,
                "IncludeMid": false,
                "IncludeRight": false,
                "BaseValue": 0,
                "OverlayValue": 0,
                "Smoothing": 0,
                "IncludeItems": false,
                "StaticColor": {
                    "r": 0.0,
                    "g": 0.0,
                    "b": 0.0,
                    "a": 1.0
                }
            },
            "ColorScreenMultiplyPreset": {
                "ArtMeshMultiplyAndScreenColors": []
            },
            "HandGestureSettings": {
                "GestureLeft": "",
                "GestureRight": "",
                "GestureCombinator": "AND",
                "AllowMirroredGesture": false,
                "DeactivateExpWhenGestureNotDetected": false,
                "SecondsUntilDetection": 0.5,
                "SecondsDetected": 0.0,
                "PercentDetected": 0.0
            },
            "LoadModelSettings": {
                "LoadAtCurrentPosition": true
            },
            "Triggers": {
                "Trigger1": "Numpad3",
                "Trigger2": "",
                "Trigger3": "",
                "ScreenButton": -1
            },
            "IsGlobal": true,
            "IsActive": true,
            "Minimized": false,
            "StopsOnLastFrame": false,
            "DeactivateAfterKeyUp": false,
            "OnlyLoadOneRandomItem": false,
            "DeactivateAfterSeconds": false,
            "DeactivateAfterSecondsAmount": 10.0,
            "FadeSecondsAmount": 0.5,
            "OnScreenHotkeyColor": {
                "r": 1.0,
                "g": 1.0,
                "b": 1.0,
                "a": 1.0
            }
        },
        {
            "HotkeyID": "afe6cd52f84d4af3a2353a86e0066d50",
            "Name": "闪光",
            "Action": "ToggleExpression",
            "File": "闪光.exp3.json",
            "Folder": "",
            "Position": {
                "X": 0.0,
                "Y": 0.0,
                "Z": 0.0,
                "Rotation": 0.0
            },
            "ColorOverlay": {
                "On": false,
                "IsStaticColor": false,
                "Display": -1,
                "WindowName": "",
                "IncludeLeft": false,
                "IncludeMid": false,
                "IncludeRight": false,
                "BaseValue": 0,
                "OverlayValue": 0,
                "Smoothing": 0,
                "IncludeItems": false,
                "StaticColor": {
                    "r": 0.0,
                    "g": 0.0,
                    "b": 0.0,
                    "a": 1.0
                }
            },
            "ColorScreenMultiplyPreset": {
                "ArtMeshMultiplyAndScreenColors": []
            },
            "HandGestureSettings": {
                "GestureLeft": "",
                "GestureRight": "",
                "GestureCombinator": "AND",
                "AllowMirroredGesture": false,
                "DeactivateExpWhenGestureNotDetected": false,
                "SecondsUntilDetection": 0.5,
                "SecondsDetected": 0.0,
                "PercentDetected": 0.0
            },
            "LoadModelSettings": {
                "LoadAtCurrentPosition": true
            },
            "Triggers": {
                "Trigger1": "Numpad5",
                "Trigger2": "",
                "Trigger3": "",
                "ScreenButton": -1
            },
            "IsGlobal": true,
            "IsActive": true,
            "Minimized": false,
            "StopsOnLastFrame": false,
            "DeactivateAfterKeyUp": false,
            "OnlyLoadOneRandomItem": false,
            "DeactivateAfterSeconds": false,
            "DeactivateAfterSecondsAmount": 10.0,
            "FadeSecondsAmount": 0.5,
            "OnScreenHotkeyColor": {
                "r": 1.0,
                "g": 1.0,
                "b": 1.0,
                "a": 1.0
            }
        },
        {
            "HotkeyID": "d620edb6ebc445beaf00826d7acc9d23",
            "Name": "黑脸",
            "Action": "ToggleExpression",
            "File": "黑脸.exp3.json",
            "Folder": "",
            "Position": {
                "X": 0.0,
                "Y": 0.0,
                "Z": 0.0,
                "Rotation": 0.0
            },
            "ColorOverlay": {
                "On": false,
                "IsStaticColor": false,
                "Display": -1,
                "WindowName": "",
                "IncludeLeft": false,
                "IncludeMid": false,
                "IncludeRight": false,
                "BaseValue": 0,
                "OverlayValue": 0,
                "Smoothing": 0,
                "IncludeItems": false,
                "StaticColor": {
                    "r": 0.0,
                    "g": 0.0,
                    "b": 0.0,
                    "a": 1.0
                }
            },
            "ColorScreenMultiplyPreset": {
                "ArtMeshMultiplyAndScreenColors": []
            },
            "HandGestureSettings": {
                "GestureLeft": "",
                "GestureRight": "",
                "GestureCombinator": "AND",
                "AllowMirroredGesture": false,
                "DeactivateExpWhenGestureNotDetected": false,
                "SecondsUntilDetection": 0.5,
                "SecondsDetected": 0.0,
                "PercentDetected": 0.0
            },
            "LoadModelSettings": {
                "LoadAtCurrentPosition": true
            },
            "Triggers": {
                "Trigger1": "Numpad4",
                "Trigger2": "",
                "Trigger3": "",
                "ScreenButton": -1
            },
            "IsGlobal": true,
            "IsActive": true,
            "Minimized": false,
            "StopsOnLastFrame": false,
            "DeactivateAfterKeyUp": false,
            "OnlyLoadOneRandomItem": false,
            "DeactivateAfterSeconds": false,
            "DeactivateAfterSecondsAmount": 10.0,
            "FadeSecondsAmount": 0.5,
            "OnScreenHotkeyColor": {
                "r": 1.0,
                "g": 1.0,
                "b": 1.0,
                "a": 1.0
            }
        }
    ],
    "HotkeySettings": {
        "UseOnScreenHotkeys": false,
        "UseKeyboardHotkeys": true,
        "SendOnScreenHotkeysToPC": true,
        "OnScreenHotkeyAlpha": 75
    },
    "ArtMeshDetails": {
        "ArtMeshesExcludedFromPinning": [],
        "ArtMeshesThatDeleteItemsOnDrop": [],
        "ArtMeshSceneLightingMultipliers": [],
        "ArtMeshMultiplyAndScreenColors": []
    },
    "ParameterCustomization": {
        "ParametersExcludedFromVNetSmoothing": []
    },
    "PhysicsCustomizationSettings": {
        "PhysicsMultipliersPerPhysicsGroup": [],
        "WindMultipliersPerPhysicsGroup": [],
        "DraggingPhysicsMultipliersPerPhysicsGroup": []
    },
    "FolderInfo": {
        "HotkeyFolders": [],
        "ConfigItemFolders": []
    },
    "SavedActiveExpressions": [
        "水印.exp3.json"
    ]
}